README.rst
setup.py
flunn/__init__.py
flunn/data.py
flunn/decoder.py
flunn/encoder.py
flunn/tool.py
flunn.egg-info/PKG-INFO
flunn.egg-info/SOURCES.txt
flunn.egg-info/dependency_links.txt
flunn.egg-info/top_level.txt