Metadata-Version: 1.1
Name: flunn
Version: 1.0.0b4
Summary: Simple decoder and encoder for CBOR (fork of flynn)
Home-page: https://github.com/funny-falcon/flunn.git
Author: Sokolov Yura aka funny_falcon, Fritz Grimpen
Author-email: funny.falcon@gmail.com, fritz@grimpen.net
License: http://opensource.org/licenses/MIT
Download-URL: https://github.com/funny-falcon/flunn/tarball/v1.0.0b4
Platform: UNKNOWN
Classifier: Development Status :: 4 - Beta
Classifier: Environment :: Web Environment
Classifier: License :: OSI Approved :: MIT License
Classifier: Programming Language :: Python :: 2.7
Classifier: Programming Language :: Python :: 3
Classifier: Topic :: System :: Networking
